LICENSE
README.md
pyproject.toml
setup.py
optzer/__init__.py
optzer/cs.py
optzer/db2csv.py
optzer/db2prms.py
optzer/de.py
optzer/get_best.py
optzer/individual.py
optzer/io.py
optzer/main.py
optzer/out2md.py
optzer/out2prms.py
optzer/testfunc.py
optzer/tpe.py
optzer.egg-info/PKG-INFO
optzer.egg-info/SOURCES.txt
optzer.egg-info/dependency_links.txt
optzer.egg-info/entry_points.txt
optzer.egg-info/requires.txt
optzer.egg-info/top_level.txt