Metadata-Version: 2.1
Name: optzer
Version: 0.2.9
Summary: This program optimizes parameters in any external programs to any target propety.
Author-email: Ryo KOBAYASHI <ryo.kbys@gmail.com>
Maintainer-email: Ryo KOBAYASHI <ryo.kbys@gmail.com>
License: The MIT License (MIT)
Project-URL: Homepage, https://github.com/ryokbys/optzer
Project-URL: Documentation, http://ryokbys.web.nitech.ac.jp/contents/optzer_doc/
Project-URL: Repository, https://github.com/ryokbys/optzer
Requires-Python: >=3.8
License-File: LICENSE
Requires-Dist: numpy
Requires-Dist: docopt
Requires-Dist: scipy
Requires-Dist: multiprocess
